Metadata-Version: 2.1
Name: example_package_emanum
Version: 0.0.1
Summary: A small example package
Project-URL: Homepage, https://github.com/Emanum/stable-style-transfer
Project-URL: Bug Tracker, https://github.com/Emanum/stable-style-transfer/issues
Author-email: Manuel Eiweck <manuel.eiweck@emanum.dev>
License-File: LICENSE
Classifier: License :: OSI Approved :: MIT License
Classifier: Operating System :: OS Independent
Classifier: Programming Language :: Python :: 3
Requires-Python: >=3.8
